hellowasif/__init__.py
hellowasif/greetings.py
hellowasif-0.0.1.dist-info/METADATA
hellowasif-0.0.1.dist-info/WHEEL
hellowasif-0.0.1.dist-info/top_level.txt
hellowasif-0.0.1.dist-info/RECORD
