Metadata-Version: 2.4
Name: hellowasif
Version: 0.0.1
Summary: A demo PyPI package by Wasif
Author-email: Wasif <wasif@example.com>
License: MIT
Project-URL: Homepage, https://github.com/wasifdev/hellowasif
Classifier: Programming Language :: Python :: 3
Classifier: License :: OSI Approved :: MIT License
Classifier: Operating System :: OS Independent
Requires-Python: >=3.7
